microsoft_bonsai_api/simulator/__init__.py
microsoft_bonsai_api/simulator/client/__init__.py
microsoft_bonsai_api/simulator/client/bonsai_client.py
microsoft_bonsai_api/simulator/client/bonsai_client_async.py
microsoft_bonsai_api/simulator/client/config.py
microsoft_bonsai_api/simulator/generated/__init__.py
microsoft_bonsai_api/simulator/generated/_configuration.py
microsoft_bonsai_api/simulator/generated/_simulator_api.py
microsoft_bonsai_api/simulator/generated/aio/__init__.py
microsoft_bonsai_api/simulator/generated/aio/_configuration.py
microsoft_bonsai_api/simulator/generated/aio/_simulator_api.py
microsoft_bonsai_api/simulator/generated/aio/operations/__init__.py
microsoft_bonsai_api/simulator/generated/aio/operations/_session_operations.py
microsoft_bonsai_api/simulator/generated/models/__init__.py
microsoft_bonsai_api/simulator/generated/models/_models.py
microsoft_bonsai_api/simulator/generated/models/_models_py3.py
microsoft_bonsai_api/simulator/generated/models/_simulator_api_enums.py
microsoft_bonsai_api/simulator/generated/operations/__init__.py
microsoft_bonsai_api/simulator/generated/operations/_session_operations.py
microsoft_bonsai_api-0.1.4.dist-info/METADATA
microsoft_bonsai_api-0.1.4.dist-info/WHEEL
microsoft_bonsai_api-0.1.4.dist-info/top_level.txt
microsoft_bonsai_api-0.1.4.dist-info/RECORD
