Metadata-Version: 2.1
Name: microsoft-bonsai-api
Version: 0.1.4
Summary: API library for the Microsoft Bonsai Platform
Home-page: https://docs.microsoft.com/bonsai
Author: Microsoft Project Bonsai
Author-email: bonsaiq@microsoft.com
License: UNKNOWN
Keywords: bonsai,autonomous systems,simulation
Platform: UNKNOWN
Requires-Dist: azure-core (<2.0.0,>=1.2.0)
Requires-Dist: msrest (>=0.6.0)
